teagen/__init__.py
teagen/bundler.py
teagen/common.py
teagen/generator.py
teagen/teagen.py
teagen/tests/__init__.py
teagen/tests/conftest.py
teagen/tests/test_bundle.py
teagen/tests/api/api.yaml
teagen/tests/api/info.yaml
teagen/tests/common/common.yaml
teagen/tests/config/config.yaml
teagen-0.0.4.dist-info/LICENSE
teagen-0.0.4.dist-info/METADATA
teagen-0.0.4.dist-info/WHEEL
teagen-0.0.4.dist-info/top_level.txt
teagen-0.0.4.dist-info/RECORD
